jaxlinop/__init__.py
jaxlinop/_version.py
jaxlinop/constant_diagonal_linear_operator.py
jaxlinop/dense_linear_operator.py
jaxlinop/diagonal_linear_operator.py
jaxlinop/identity_linear_operator.py
jaxlinop/linear_operator.py
jaxlinop/triangular_linear_operator.py
jaxlinop/utils.py
jaxlinop/zero_linear_operator.py
jaxlinop_nightly-0.0.4.dev20230318.dist-info/METADATA
jaxlinop_nightly-0.0.4.dev20230318.dist-info/WHEEL
jaxlinop_nightly-0.0.4.dev20230318.dist-info/top_level.txt
jaxlinop_nightly-0.0.4.dev20230318.dist-info/zip-safe
jaxlinop_nightly-0.0.4.dev20230318.dist-info/RECORD
