Metadata-Version: 2.1
Name: jaxlinop-nightly
Version: 0.0.4.dev20230318
Summary: A JaxLinOp library.
Home-page: https://github.com/JaxGaussianProcesses/JaxLinOp
Author: Daniel Dodd, Thomas Pinder
Author-email: d.dodd1@lancaster.ac.uk, tompinder@live.co.uk
Maintainer: Daniel Dodd, Thomas Pinder
Maintainer-email: d.dodd1@lancaster.ac.uk, tompinder@live.co.uk
License: Apache 2.0
Requires-Python: >=3.6
Requires-Dist: jax (>=0.4.1)
Requires-Dist: jaxlib (>=0.4.1)
Requires-Dist: jaxtyping
Requires-Dist: simple-pytree
Provides-Extra: dev
Requires-Dist: pytest ; extra == 'dev'
Requires-Dist: pre-commit ; extra == 'dev'
Requires-Dist: pytest-cov ; extra == 'dev'
